[
    {
        "id": "ce035e2f6f094766",
        "type": "tab",
        "label": "5: Flow1",
        "disabled": false,
        "info": "",
        "env": []
    },
    {
        "id": "43d1740e38cc6310",
        "type": "tls-config",
        "name": "mqtt.lora.eagelcovewc.com",
        "cert": "",
        "key": "",
        "ca": "",
        "certname": "mqtt_client.pem",
        "keyname": "mqtt_client.key",
        "caname": "ca.pem",
        "servername": "mqtt.lora.eagelcovewc.com",
        "verifyservercert": true,
        "alpnprotocol": ""
    },
    {
        "id": "9d156d3c3c4f5a59",
        "type": "telegram bot",
        "botname": "SJI IOT BOT",
        "usernames": "",
        "chatids": "",
        "baseapiurl": "",
        "testenvironment": false,
        "updatemode": "polling",
        "pollinterval": 300,
        "usesocks": false,
        "sockshost": "",
        "socksprotocol": "socks5",
        "socksport": 6667,
        "socksusername": "anonymous",
        "sockspassword": "",
        "bothost": "",
        "botpath": "",
        "localbothost": "0.0.0.0",
        "localbotport": 8443,
        "publicbotport": 8443,
        "privatekey": "",
        "certificate": "",
        "useselfsignedcertificate": false,
        "sslterminated": false,
        "verboselogging": false
    },
    {
        "id": "b79a80b523e80429",
        "type": "mqtt-broker",
        "name": "mqtt.lora.ecwc.com",
        "broker": "mqtt.lora.eaglecovewc.com",
        "port": "8883",
        "tls": "43d1740e38cc6310",
        "clientid": "",
        "autoConnect": true,
        "usetls": true,
        "protocolVersion": 4,
        "keepalive": 60,
        "cleansession": true,
        "autoUnsubscribe": true,
        "birthTopic": "",
        "birthQos": "0",
        "birthRetain": "false",
        "birthPayload": "",
        "birthMsg": {},
        "closeTopic": "",
        "closeQos": "0",
        "closeRetain": "false",
        "closePayload": "",
        "closeMsg": {},
        "willTopic": "",
        "willQos": "0",
        "willRetain": "false",
        "willPayload": "",
        "willMsg": {},
        "userProps": "",
        "sessionExpiry": ""
    },
    {
        "id": "766e0213db921d4c",
        "type": "chirpstack-server",
        "server": "10.8.0.1:8080"
    },
    {
        "id": "efd5c596d901410c",
        "type": "mqtt in",
        "z": "ce035e2f6f094766",
        "name": "ECWC Infrastructure Meter",
        "topic": "application/158daf48-5c45-4c73-88ee-75358c8f5323/device/+/event/up",
        "qos": "0",
        "datatype": "auto-detect",
        "broker": "b79a80b523e80429",
        "nl": false,
        "rap": true,
        "rh": 0,
        "inputs": 0,
        "x": 310,
        "y": 400,
        "wires": [
            [
                "05e9c02681cb4969",
                "7ed9cbb3230aa9fe",
                "d08923424dad4b7e"
            ]
        ]
    },
    {
        "id": "05e9c02681cb4969",
        "type": "telegram sender",
        "z": "ce035e2f6f094766",
        "name": "Humidity Sender",
        "bot": "9d156d3c3c4f5a59",
        "haserroroutput": true,
        "outputs": 2,
        "x": 670,
        "y": 280,
        "wires": [
            [],
            []
        ]
    },
    {
        "id": "18aec99d112e431d",
        "type": "comment",
        "z": "ce035e2f6f094766",
        "name": "Group 5 LoRaWAN Info",
        "info": "## Group 5 - LoRaWAN Device Info\n\n**Application ID:** `158daf48-5c45-4c73-88ee-75358c8f5323`\n**MQTT Topic:** `application/158daf48-5c45-4c73-88ee-75358c8f5323/device/+/event/up`\n**Telegram Chat ID:** `-5201535256`\n**All-groups Chat ID:** `-5144508977`\n\n### Relay 5 (4 Channel Relay)\n- **DEV EUI:** `48E663FFFE301020`\n- **APP EUI:** `48FF000000001020`\n- **APP KEY:** `4597658061A3698C78521ADCFE4B3C78`\n\n### TempHum5 (Temp & Humid Sensor)\n- **DEV EUI:** `48E663FFFE3010EA`\n- **APP EUI:** `48FF0000000010EA`\n- **APP KEY:** `6CDED7C5F00999F100B97BC68AD33220`\n\n---\n**Telegram for Windows:** [Download](https://telegram.org/dl/desktop/win)\n\n**AgroSense Sensor Manual:** [PDF](https://github.com/Makerfabs/Agrosense-Decoder/blob/main/Agrosense_Air_Temperature_Humidity_Sensor/AgroSense_Air%20Temperature%20and%20Humidity%20Sensor%20LoRaWAN%C2%AE%20Manual%20V1.2.pdf)\n\n**Telegram Web App:** [Open](https://web.telegram.org/k/)\n**Node-RED Telegram Docs:** [flows.nodered.org](https://flows.nodered.org/node/node-red-contrib-telegrambot)\nhttps://t.me/+WY5m7Pdn48s4OWE5",
        "x": 220,
        "y": 20,
        "wires": []
    },
    {
        "id": "7ed9cbb3230aa9fe",
        "type": "debug",
        "z": "ce035e2f6f094766",
        "name": "debug 1",
        "active": true,
        "tosidebar": true,
        "console": false,
        "tostatus": false,
        "complete": "true",
        "targetType": "full",
        "statusVal": "",
        "statusType": "auto",
        "x": 740,
        "y": 540,
        "wires": []
    },
    {
        "id": "a717b87011af4274",
        "type": "e-mail",
        "z": "ce035e2f6f094766",
        "server": "smtp.gmail.com",
        "port": "465",
        "authtype": "BASIC",
        "saslformat": true,
        "token": "oauth2Response.access_token",
        "secure": true,
        "tls": true,
        "name": "smithlum000@stu.sjisd.org",
        "dname": "IOT BOT Email",
        "x": 840,
        "y": 400,
        "wires": []
    },
    {
        "id": "36cf813c2bcc5dfa",
        "type": "chirpstack-enqueue",
        "z": "ce035e2f6f094766",
        "name": "Relay Port",
        "server": "766e0213db921d4c",
        "devEui": "48e663fffe30085a",
        "applicationId": "",
        "fPort": "",
        "confirmed": true,
        "debug": false,
        "x": 530,
        "y": 80,
        "wires": [
            []
        ]
    },
    {
        "id": "bc66ae0b4d0e7882",
        "type": "inject",
        "z": "ce035e2f6f094766",
        "name": "",
        "props": [
            {
                "p": "payload"
            },
            {
                "p": "topic",
                "vt": "str"
            }
        ],
        "repeat": "",
        "crontab": "",
        "once": false,
        "onceDelay": 0.1,
        "topic": "test99",
        "payload": "hello world",
        "payloadType": "str",
        "x": 320,
        "y": 520,
        "wires": [
            [
                "a717b87011af4274",
                "a7fdb08685acf5c5"
            ]
        ]
    },
    {
        "id": "a7fdb08685acf5c5",
        "type": "debug",
        "z": "ce035e2f6f094766",
        "name": "debug 2",
        "active": true,
        "tosidebar": true,
        "console": false,
        "tostatus": false,
        "complete": "true",
        "targetType": "full",
        "statusVal": "",
        "statusType": "auto",
        "x": 600,
        "y": 640,
        "wires": []
    },
    {
        "id": "d08923424dad4b7e",
        "type": "function",
        "z": "ce035e2f6f094766",
        "name": "function 1",
        "func": "\nreturn msg;",
        "outputs": 1,
        "timeout": 0,
        "noerr": 0,
        "initialize": "",
        "finalize": "",
        "libs": [],
        "x": 580,
        "y": 400,
        "wires": [
            [
                "a717b87011af4274"
            ]
        ]
    },
    {
        "id": "2e3e4702cd07846e",
        "type": "comment",
        "z": "ce035e2f6f094766",
        "name": "field 2",
        "info": "field 2: humidity",
        "x": 350,
        "y": 640,
        "wires": []
    },
    {
        "id": "8beaa89f7c0c975e",
        "type": "comment",
        "z": "ce035e2f6f094766",
        "name": "field 3",
        "info": "field 3: temperature (celsius)",
        "x": 350,
        "y": 680,
        "wires": []
    },
    {
        "id": "c899249f960cac3f",
        "type": "comment",
        "z": "ce035e2f6f094766",
        "name": "field 4",
        "info": "field 4: time (seconds)",
        "x": 350,
        "y": 720,
        "wires": []
    },
    {
        "id": "63361651947f4952",
        "type": "delay",
        "z": "ce035e2f6f094766",
        "name": "",
        "pauseType": "delay",
        "timeout": "5",
        "timeoutUnits": "hours",
        "rate": "1",
        "nbRateUnits": "1",
        "rateUnits": "second",
        "randomFirst": "1",
        "randomLast": "5",
        "randomUnits": "seconds",
        "drop": false,
        "allowrate": false,
        "outputs": 1,
        "x": 180,
        "y": 580,
        "wires": [
            []
        ]
    },
    {
        "id": "a136e5e806930228",
        "type": "comment",
        "z": "ce035e2f6f094766",
        "name": "field 1",
        "info": "field 1: voltage",
        "x": 350,
        "y": 600,
        "wires": []
    }
]